LICENSE
clouddrive/__init__.py
clouddrive/__init_client.py
clouddrive/__main__.py
clouddrive/client.py
clouddrive/cmd/__init__.py
clouddrive/cmd/download.py
clouddrive/cmd/fuse/__init__.py
clouddrive/cmd/fuse/__main__.py
clouddrive/cmd/fuse/util/__fuse_monkey_patch.py
clouddrive/cmd/fuse/util/__init__.py
clouddrive/cmd/fuse/util/fuser.py
clouddrive/cmd/fuse/util/log.py
clouddrive/cmd/fuse/util/predicate.py
clouddrive/cmd/fuse/util/strm.py
clouddrive/cmd/init.py
clouddrive/cmd/iterdir.py
clouddrive/cmd/rename.py
clouddrive/cmd/upload.py
clouddrive/pb2.py
clouddrive/proto/CloudDrive.proto
clouddrive/proto/CloudDrive_grpc.py
clouddrive/proto/CloudDrive_pb2.py
clouddrive/proto/CloudDrive_pb2_grpc.py
clouddrive/py.typed
clouddrive-0.0.12.7.1.dist-info/LICENSE
clouddrive-0.0.12.7.1.dist-info/METADATA
clouddrive-0.0.12.7.1.dist-info/WHEEL
clouddrive-0.0.12.7.1.dist-info/entry_points.txt
clouddrive-0.0.12.7.1.dist-info/RECORD
