Metadata-Version: 2.1
Name: clouddrive
Version: 0.0.12.7.1
Summary: Python wrapper for CloudDrive.
Home-page: https://github.com/ChenyangGao/web-mount-packs/tree/main/python-clouddrive-client
License: MIT
Keywords: client,clouddrive
Author: ChenyangGao
Author-email: wosiwujm@gmail.com
Requires-Python: >=3.10,<4.0
Classifier: Development Status :: 4 - Beta
Classifier: Intended Audience :: Developers
Classifier: License :: OSI Approved :: MIT License
Classifier: Operating System :: OS Independent
Classifier: Programming Language :: Python
Classifier: Programming Language :: Python :: 3
Classifier: Programming Language :: Python :: 3.10
Classifier: Programming Language :: Python :: 3.11
Classifier: Programming Language :: Python :: 3.12
Classifier: Programming Language :: Python :: 3.13
Classifier: Programming Language :: Python :: 3 :: Only
Classifier: Topic :: Software Development
Classifier: Topic :: Software Development :: Libraries
Classifier: Topic :: Software Development :: Libraries :: Python Modules
Requires-Dist: glob_pattern
Requires-Dist: grpcio
Requires-Dist: grpcio-tools
Requires-Dist: grpclib
Requires-Dist: grpclib[protobuf]
Requires-Dist: http_response
Requires-Dist: path_ignore_pattern
Requires-Dist: protobuf
Requires-Dist: python-argtools
Requires-Dist: python-dateutil
Requires-Dist: python-download (>=0.0.3)
Requires-Dist: python-filewrap (>=0.1.1)
Requires-Dist: python-http_request (>=0.0.6)
Requires-Dist: python-httpfile (>=0.0.2)
Requires-Dist: python-urlopen
Requires-Dist: yarl
Project-URL: Repository, https://github.com/ChenyangGao/web-mount-packs/tree/main/python-clouddrive-client
